edenpy/__init__.py
edenpy/edenpy.py
edenpy/logger.py
edenpy/losafile.py
edenpy/slack.py
edenpy-0.5.6.dist-info/METADATA
edenpy-0.5.6.dist-info/WHEEL
edenpy-0.5.6.dist-info/top_level.txt
edenpy-0.5.6.dist-info/RECORD
