Metadata-Version: 2.1
Name: edenpy
Version: 0.5.6
Summary: Personal utils package for Python projects
Home-page: https://github.com/dlems/py-utils
Author: dlems
Author-email: 
License: UNKNOWN
Keywords: utils
Platform: UNKNOWN
Classifier: Programming Language :: Python :: 3.7
Requires-Python: >=3.7
